aquasol/__init__.py
aquasol/__main__.py
aquasol/config.py
aquasol/constants.py
aquasol/format.py
aquasol/humidity.py
aquasol/properties.py
aquasol/formulas/__init__.py
aquasol/formulas/general.py
aquasol/formulas/solutions/__init__.py
aquasol/formulas/solutions/basic_conversions.py
aquasol/formulas/solutions/ionic.py
aquasol/formulas/solutions/pitzer.py
aquasol/formulas/solutions/steiger.py
aquasol/formulas/solutions/activity_coefficient/KCl.py
aquasol/formulas/solutions/activity_coefficient/LiBr.py
aquasol/formulas/solutions/activity_coefficient/LiCl.py
aquasol/formulas/solutions/activity_coefficient/Na2SO4.py
aquasol/formulas/solutions/activity_coefficient/NaCl.py
aquasol/formulas/solutions/activity_coefficient/__init__.py
aquasol/formulas/solutions/activity_coefficient/pitzer.py
aquasol/formulas/solutions/activity_coefficient/steiger.py
aquasol/formulas/solutions/activity_coefficient/tang.py
aquasol/formulas/solutions/data/Coeffs_Steiger2005_Activity.json
aquasol/formulas/solutions/data/Coeffs_Steiger2008_Activity.json
aquasol/formulas/solutions/data/Coeffs_Steiger2008_Solubility.json
aquasol/formulas/solutions/density/CaCl2.py
aquasol/formulas/solutions/density/KCl.py
aquasol/formulas/solutions/density/KI.py
aquasol/formulas/solutions/density/LiCl.py
aquasol/formulas/solutions/density/MgCl2.py
aquasol/formulas/solutions/density/Na2SO4.py
aquasol/formulas/solutions/density/NaCl.py
aquasol/formulas/solutions/density/__init__.py
aquasol/formulas/solutions/density/al_ghafri.py
aquasol/formulas/solutions/density/clegg.py
aquasol/formulas/solutions/density/glycerol.py
aquasol/formulas/solutions/density/krumgalz.py
aquasol/formulas/solutions/density/misc.py
aquasol/formulas/solutions/density/tang.py
aquasol/formulas/solutions/density/volk.py
aquasol/formulas/solutions/electrical_conductivity/KCl.py
aquasol/formulas/solutions/electrical_conductivity/NaCl.py
aquasol/formulas/solutions/electrical_conductivity/__init__.py
aquasol-1.8.1.dist-info/licenses/LICENSE
aquasol-1.8.1.dist-info/METADATA
aquasol-1.8.1.dist-info/WHEEL
aquasol-1.8.1.dist-info/top_level.txt
aquasol-1.8.1.dist-info/RECORD
