Metadata-Version: 2.4
Name: aquasol
Version: 1.8.1
Summary: Thermodynamic and physico-chemical properties for water and aqueous solutions
Author-email: Olivier Vincent <ovinc.py@gmail.com>
License: CeCILL-2.1
Project-URL: Homepage, https://github.com/ovinc/aquasol
Project-URL: Documentation, https://github.com/ovinc/aquasol/README.md
Project-URL: Repository, https://github.com/ovinc/aquasol.git
Keywords: water,solutions,salt,thermodynamic,properties,relations,convert,IAPWS,supersaturated,supersaturation,pitzer,kelvin,activity,volumetric,vapor_pressure,dewpoint,density,surface tension,viscosity,diffusivity,solubility,activity coefficient,osmotic,refractive index,electrical conductivity,physics,chemistry
Classifier: Programming Language :: Python :: 3
Classifier: Operating System :: OS Independent
Classifier: License :: OSI Approved :: CEA CNRS Inria Logiciel Libre License, version 2.1 (CeCILL-2.1)
Requires-Python: >=3.6
License-File: LICENSE
Requires-Dist: numpy
Requires-Dist: pynverse
Requires-Dist: importlib-metadata
Dynamic: license-file
